<?xml version="1.0" encoding="UTF-8" ?>
<!DOCTYPE mapper PUBLIC "-//mybatis.org//DTD Mapper 3.0//EN" "http://mybatis.org/dtd/mybatis-3-mapper.dtd" >
<mapper namespace="com.itheima.dao.SetmealDao">
    <insert id="add" parameterType="Setmeal">
        INSERT t_setmeal
        VALUES (null, #{name}, #{code}, #{helpCode},#{sex},#{age},#{price}, #{remark}, #{attention}, #{img})
        <selectKey resultType="integer" order="AFTER" keyProperty="id">
            Select LAST_INSERT_ID()
        </selectKey>
    </insert>
    <insert id="setRelation">
        INSERT into t_setmeal_checkgroup
        VALUES (#{setmeal_id},#{checkgroup_id})
    </insert>

    <!--根据条件查询-->
    <select id="findByCondition" resultType="setmeal">
        SELECT * FROM t_setmeal
        <if test="queryString!=null and queryString.length > 0">
            WHERE code LIKE CONCAT('%',#{queryString},'%') or name LIKE CONCAT('%',#{queryString},'%') or helpCode like CONCAT('%',#{queryString},'%')
        </if>
    </select>

    <select id="findAll" resultType="setmeal">
        select * from t_setmeal
    </select>

    <!--映射基本字段-->
    <resultMap id="baseMap" type="setmeal">
        <id column="id" property="id"></id>
        <result column="name" property="name"></result>
        <result column="code" property="code"></result>
        <result column="helpCode" property="helpCode"></result>
        <result column="sex" property="sex"></result>
        <result column="age" property="age"></result>
        <result column="remark" property="remark"></result>
        <result column="price" property="price"></result>
        <result column="attention" property="attention"></result>
        <result column="img" property="img"></result>
    </resultMap>

    <resultMap id="findDetailsByIdMap" type="setmeal" extends="baseMap">
        <!--一对多关联-->
        <!--
                  fetchType="lazy": 懒加载
                  property： 对应属性名
                  column： 对应列名（已知条件的）（一定是sql的结果集中存在的列）
                  ofType: 属性的泛型
                  select： 可以sql语句，方法的唯一标识（全名称=包名+类名 + 方法名）
                          //根据套餐id查询检查组的数据
                          List<CheckGroup> com.itheima.dao.CheckGroupDao.findCheckGroupListBySetmealId(Integer setmealId)

              -->
        <collection
                property="checkGroups"
                column="id"
                ofType="checkGroup"
                select="com.itheima.dao.CheckGroupDao.findCheckGroupListBySetmealId"></collection>
    </resultMap>

    <!--
                如果属性名与列名不一致，使用结果映射
        -->
    <select id="findDetailsById" parameterType="int" resultMap="findDetailsByIdMap">
        select * from t_setmeal where id = #{id}
    </select>

    <select id="findById" parameterType="int" resultType="setmeal">
        select * from t_setmeal where id = #{id}
    </select>


</mapper>